README.md
setup.py
tCafeteria/tCafeteria.py
tanbang_cafeteria.egg-info/PKG-INFO
tanbang_cafeteria.egg-info/SOURCES.txt
tanbang_cafeteria.egg-info/dependency_links.txt
tanbang_cafeteria.egg-info/entry_points.txt
tanbang_cafeteria.egg-info/requires.txt
tanbang_cafeteria.egg-info/top_level.txt