Metadata-Version: 1.0
Name: tanbang-cafeteria
Version: 0.1
Summary: Parse schedule & cafeteria
Home-page: UNKNOWN
Author: w3bn00b
Author-email: powderbanana@gmail.com
License: UNKNOWN
Platform: UNKNOWN
